{"countryCode":"VG","countryName":"Virgin Islands, British","cityCount":141,"splitByChar":true,"dataArray":["Albion","Apple Bay","Arundell","Bakers Bay","Ballast Bay","Balsom Ghut","Belle Vue","Belmont","Blyden","Boway","Brandywine Bay","Cane Garden Bay","Cappoons Bay","Carrot Bay","Cart Path","Chalwell","Cocodella","Cooten Bay","Cotton Ground","Daseys","Dawson","Diamond","Doty","Duffs Bottom","East End","Edney","Fahie Hill","Fish Bay","Freshwater Pond","Georges Hollow","Green Bank","Havers","Hawks Nest","Henley","Hodge","Hodge\u0027s Creek","Josias Bay","Kingstown","Lambert","Leonards","Lettsome Settlement","Little Apple Bay","Little Dix Bay","Little Harbour","Long Bay","Long Swamp","Lower Hope","Martin","Martins Joes Hill","Maya Cove","McIntosh","Meyers","Mount Healthy","New Bush","Nibbs","North Sound Settlement","North Sound","Nottingham Estate","Paraquita Bay","Parham Town","Pickering","Pleasant Valley","Pockwood Pond","Pond Bay","Primrose Garden","Recovery","Rhymers Estate","Road Town","Rogues Bay","Ross","Shannon","Slaney","Spanish Town","Spooner","Spring Bay Land","Steep Hill","The Bond","The Country","The Settlement","Trunk Bay","Turnbull Hill","Upper Hope","Wesley Will","West End","Anderson","Copper Mine","Creek Village","Great Carrot Bay","Great Mountain","Hannah","Hedrington Spring Ghut","John Tarter","Little Carrot Bay","Lloyds","Martin Spring Ghut","Plum Tree Bay","Skeleton Land","South Side","South Sound","The Mill","Thomas Land","Threllfall","Trunk Bay Land","Baughers Bay","Blyden Yard","Church Hill","Crab Hill","Fanny Mac Hill","Fat Hogs Bay","Fisher Estate","Fort Hill","Free Bottom","Greenland","Handsome Bay","Harrigan Pasture","Head of the Bay","Hodge Estate","Huntums Ghut","James Young","Johnson Ghut","John\u0027s Hole","Long Bush","Long Look","Lower Estate","Major Bay","McNamara","Old Plantation","Pasea Estate","Princess Quarters","Purcell","Red Bay","Road Reef","Russell Hill","Stevens Pasture","Tarris Hill","Taylors Bay","Town Bay","Vanterpool","Wickhams Cay One","Wickhams Cay Two","Windy Hill"],"dataHash":{"The Mill":1,"Old Plantation":1,"Trunk Bay Land":1,"Nibbs":1,"North Sound":1,"Belmont":1,"Major Bay":1,"Little Harbour":1,"Johnson Ghut":1,"Henley":1,"South Side":1,"Little Dix Bay":1,"Chalwell":1,"Pond Bay":1,"Mount Healthy":1,"Plum Tree Bay":1,"Crab Hill":1,"Paraquita Bay":1,"Head of the Bay":1,"Josias Bay":1,"Upper Hope":1,"Huntums Ghut":1,"Meyers":1,"McNamara":1,"Pockwood Pond":1,"Lambert":1,"Hodge Estate":1,"Carrot Bay":1,"Albion":1,"Cappoons Bay":1,"John Tarter":1,"Maya Cove":1,"Dawson":1,"Tarris Hill":1,"Long Look":1,"Spooner":1,"Thomas Land":1,"Creek Village":1,"Road Reef":1,"Lloyds":1,"Doty":1,"Hawks Nest":1,"Lower Hope":1,"Turnbull Hill":1,"Fish Bay":1,"Pickering":1,"Martins Joes Hill":1,"Parham Town":1,"Ross":1,"Slaney":1,"Hodge\u0027s Creek":1,"Fisher Estate":1,"Fanny Mac Hill":1,"Green Bank":1,"Lettsome Settlement":1,"Red Bay":1,"Cocodella":1,"Bakers Bay":1,"Stevens Pasture":1,"Town Bay":1,"Martin":1,"Long Bay":1,"Blyden Yard":1,"Cotton Ground":1,"Belle Vue":1,"Spring Bay Land":1,"Fahie Hill":1,"Spanish Town":1,"Edney":1,"Long Swamp":1,"John\u0027s Hole":1,"Freshwater Pond":1,"Little Apple Bay":1,"South Sound":1,"Long Bush":1,"Shannon":1,"Kingstown":1,"Recovery":1,"Hodge":1,"Rogues Bay":1,"Cane Garden Bay":1,"McIntosh":1,"Free Bottom":1,"Apple Bay":1,"Blyden":1,"Copper Mine":1,"Rhymers Estate":1,"Wesley Will":1,"Taylors Bay":1,"The Settlement":1,"Daseys":1,"Havers":1,"Great Carrot Bay":1,"East End":1,"Pasea Estate":1,"Martin Spring Ghut":1,"Little Carrot Bay":1,"Fat Hogs Bay":1,"Russell Hill":1,"Steep Hill":1,"Harrigan Pasture":1,"Boway":1,"Primrose Garden":1,"Skeleton Land":1,"Cart Path":1,"Church Hill":1,"Baughers Bay":1,"Fort Hill":1,"Purcell":1,"Princess Quarters":1,"Brandywine Bay":1,"Windy Hill":1,"Road Town":1,"New Bush":1,"Ballast Bay":1,"North Sound Settlement":1,"Duffs Bottom":1,"Vanterpool":1,"Handsome Bay":1,"West End":1,"Georges Hollow":1,"Cooten Bay":1,"Pleasant Valley":1,"Hannah":1,"Great Mountain":1,"Diamond":1,"Lower Estate":1,"Leonards":1,"Threllfall":1,"Anderson":1,"Nottingham Estate":1,"Wickhams Cay One":1,"The Country":1,"Balsom Ghut":1,"The Bond":1,"Trunk Bay":1,"Wickhams Cay Two":1,"Hedrington Spring Ghut":1,"James Young":1,"Arundell":1,"Greenland":1},"subDataHash":{" ":123,"\u0027":2,"A":5,"B":46,"C":19,"D":6,"E":10,"F":8,"G":13,"H":30,"I":1,"J":6,"K":1,"L":19,"M":13,"N":7,"O":2,"P":17,"Q":1,"R":9,"S":20,"T":18,"U":1,"V":4,"W":6,"Y":2,"a":130,"b":7,"c":12,"d":41,"e":129,"f":5,"g":21,"h":40,"i":51,"j":1,"k":13,"l":81,"m":23,"n":97,"o":100,"p":20,"q":1,"r":79,"s":67,"t":90,"u":37,"v":4,"w":18,"x":1,"y":53},"markovHash":{"\nSk":{"e":1.0},"\nSl":{"a":1.0},"\nSo":{"u":2.0},"\nSp":{"a":1.0,"r":1.0,"o":1.0},"ion":{"\n":2.0},"\n":{"\n":141.0},"\nSt":{"e":2.0},"rab":{" ":1.0},"tee":{"p":1.0},"r B":{"a":1.0},"r E":{"s":2.0},"\nTa":{"r":1.0,"y":1.0},"r H":{"o":2.0},"ten":{" ":1.0},"ran":{"d":1.0},"\nTh":{"r":1.0,"e":4.0,"o":1.0},"r M":{"i":1.0},"ab ":{"H":1.0},"ter":{" ":1.0,"p":1.0,"s":1.0,"\n":1.0},"r P":{"o":1.0},"raq":{"u":1.0},"tev":{"e":1.0},"\nTo":{"w":1.0},"\nTr":{"u":2.0},"\nTu":{"r":1.0},"th ":{"S":4.0},"is ":{"H":1.0},"ek ":{"V":1.0},"rbo":{"u":1.0},"ac ":{"H":1.0},"a B":{"a":1.0},"a C":{"o":1.0},"\nUp":{"p":1.0},"a E":{"s":1.0},"cel":{"l":1.0},"e\u0027s":{" ":1.0},"The":{" ":4.0},"ces":{"s":1.0},"rce":{"l":1.0},"\nVa":{"n":1.0},"rch":{" ":1.0},"Tho":{"m":1.0},"ch ":{"H":1.0},"ad ":{"R":1.0,"T":1.0,"o":1.0},"Thr":{"e":1.0}," Ap":{"p":1.0},"the":{" ":1.0},"Red":{" ":1.0},"Rec":{"o":1.0},"rde":{"n":2.0},"Ree":{"f":1.0},"\u0027s ":{"C":1.0,"H":1.0},"\nWe":{"s":2.0},"\nWi":{"c":2.0,"n":1.0},"Cha":{"l":1.0}," Ba":{"y":30.0,"n":1.0},"ish":{" ":2.0,"e":1.0},"rds":{"\n":1.0},"Par":{"a":1.0,"h":1.0},"Pat":{"h":1.0},"kwo":{"o":1.0},"Pas":{"t":2.0,"e":1.0},"thy":{"\n":1.0}," Bo":{"t":2.0,"n":1.0},"rea":{"t":2.0},"Chu":{"r":1.0},"ree":{" ":2.0,"k":2.0,"n":2.0}," Bu":{"s":2.0},"en ":{"B":3.0,"Y":1.0},"ita":{" ":1.0},"tin":{" ":1.0,"s":1.0,"g":1.0,"\n":1.0},"rel":{"l":1.0},"p H":{"i":1.0},"tio":{"n":1.0},"pan":{"i":1.0}," Ca":{"r":2.0,"y":2.0},"ele":{"t":1.0},"res":{"h":1.0},"ell":{" ":1.0,"a":1.0,"e":1.0,"f":1.0,"\n":3.0},"elm":{"o":1.0},"itt":{"l":4.0}," Co":{"u":1.0,"v":1.0}," Cr":{"e":1.0},"gs ":{"B":1.0},"End":{"\n":2.0},"Gre":{"a":2.0,"e":2.0},"eme":{"n":3.0},"Gro":{"u":1.0}," Di":{"x":1.0},"ix ":{"B":1.0},"rge":{"s":1.0},"ep ":{"H":1.0},"enl":{"a":1.0,"e":1.0},"Rhy":{"m":1.0}," En":{"d":2.0},"ent":{"\n":3.0},"rha":{"m":1.0},"ens":{" ":1.0},"tle":{" ":4.0,"m":3.0}," Es":{"t":6.0},"Nam":{"a":1.0},"cke":{"r":1.0},"age":{"\n":1.0},"ckh":{"a":2.0},"eon":{"a":1.0},"eor":{"g":1.0},"gst":{"o":1.0},"ckw":{"o":1.0},"n B":{"a":4.0},"rig":{"a":1.0},"er ":{"P":1.0,"E":2.0,"H":2.0,"M":1.0},"n G":{"r":1.0,"h":1.0},"nah":{"\n":1.0},"rin":{"c":1.0,"g":5.0},"rim":{"r":1.0}," Ga":{"r":2.0},"n L":{"a":1.0},"per":{" ":2.0},"ris":{" ":1.0},"nar":{"d":1.0},"n P":{"a":1.0},"n S":{"p":2.0}," Gh":{"u":5.0},"ahi":{"e":1.0},"gto":{"n":1.0},"n T":{"a":1.0},"n Y":{"a":1.0}," Gr":{"o":1.0},"nd ":{"B":1.0,"S":1.0},"es ":{"B":1.0,"H":2.0,"Y":1.0},"gue":{"s":1.0}," Ha":{"r":1.0}," He":{"a":1.0},"Tow":{"n":4.0},"\n\n":{"\n":141.0},"nbu":{"l":1.0}," Hi":{"l":11.0}," Ho":{"p":2.0,"g":1.0,"l":2.0},"ain":{"\n":1.0},"ne ":{"B":1.0,"G":1.0},"nce":{"s":1.0},"ton":{" ":3.0},"tom":{"\n":2.0},"Coc":{"o":1.0},"tos":{"h":1.0},"tow":{"n":1.0},"eri":{"n":1.0},"Coo":{"t":1.0},"erp":{"o":1.0},"Cop":{"p":1.0},"ert":{"\n":1.0},"ers":{" ":3.0,"\n":3.0,"o":1.0},"Vue":{"\n":1.0},"Est":{"a":6.0},"ajo":{"r":1.0},"Cou":{"n":1.0},"Cot":{"t":1.0},"Cov":{"e":1.0},"Pic":{"k":1.0},"ery":{"\n":1.0},"nde":{"r":1.0,"l":1.0},"am ":{"T":1.0,"E":1.0},"Alb":{"i":1.0},"Lan":{"d":4.0},"cod":{"e":1.0},"Lam":{"b":1.0},"ake":{"r":1.0},"esh":{"w":1.0},"nds":{"o":1.0},"Nes":{"t":1.0},"esl":{"e":1.0},"New":{" ":1.0},"ndy":{" ":1.0,"w":1.0},"ess":{" ":1.0}," Jo":{"e":1.0},"ng ":{"B":3.0,"S":1.0,"G":2.0,"L":1.0},"Tre":{"e":1.0},"est":{" ":1.0,"\n":1.0},"cov":{"e":1.0},"an ":{"P":1.0},"lag":{"e":1.0},"l H":{"i":2.0},"Tru":{"n":2.0},"lan":{"d":1.0,"t":1.0,"e":1.0},"ner":{"\n":1.0},"las":{"t":1.0},"all":{"a":1.0,"e":1.0,"\n":1.0},"eto":{"n":1.0},"ney":{"\n":2.0},"ett":{"s":1.0,"l":3.0},"Roa":{"d":2.0},"rnb":{"u":1.0},"alt":{"h":1.0},"als":{"o":1.0},"ld ":{"P":1.0},"Rog":{"u":1.0},"alw":{"e":1.0},"ew ":{"B":1.0},"lbi":{"o":1.0},"Cra":{"b":1.0},"ama":{"r":1.0}," La":{"n":4.0},"And":{"e":1.0},"Cre":{"e":2.0},"amb":{"e":1.0},"Ros":{"s":1.0},"ame":{"s":1.0},"try":{"\n":1.0},"amo":{"n":1.0}," Lo":{"o":1.0},"Pla":{"n":1.0},"amp":{"\n":1.0},"le ":{"A":1.0,"B":2.0,"C":1.0,"D":1.0,"V":1.0,"H":1.0},"ams":{" ":2.0},"Ple":{"a":1.0},"ngh":{"a":1.0},"tso":{"m":1.0}," Ma":{"c":1.0},"eve":{"n":1.0},"and":{"s":1.0,"y":1.0,"\n":5.0},"rot":{" ":3.0},"ros":{"e":1.0},"Plu":{"m":1.0},"ane":{" ":1.0,"y":1.0},"rou":{"n":1.0},"ngt":{"o":1.0},"ngs":{"t":1.0}," Mi":{"l":1.0,"n":1.0},"ani":{"s":1.0},"ank":{"\n":1.0},"ann":{"a":1.0,"y":1.0,"o":1.0}," Mo":{"u":1.0},"Nib":{"b":1.0},"ant":{" ":1.0,"a":1.0,"e":1.0},"ple":{" ":2.0},"tti":{"n":1.0},"ttl":{"e":7.0},"ey ":{"W":1.0},"tto":{"m":2.0,"n":1.0},"Tur":{"n":1.0},"rpo":{"o":1.0},"tts":{"o":1.0}," Ne":{"s":1.0},"Leo":{"n":1.0},"Jam":{"e":1.0},"Let":{"t":1.0},"rs ":{"B":3.0,"E":1.0},"App":{"l":2.0},"nk ":{"B":2.0},"lea":{"s":1.0},"tum":{"s":1.0},"tur":{"e":2.0},"lem":{"e":3.0},"ya ":{"C":1.0},"nis":{"h":1.0},"let":{"o":1.0},"n\u0027s":{" ":1.0},"rt ":{"P":1.0,"H":1.0}," On":{"e":1.0},"app":{"o":1.0},"ley":{" ":1.0,"\n":2.0},"Poc":{"k":1.0},"lfa":{"l":1.0},"rri":{"s":1.0,"g":1.0},"Two":{"\n":1.0},"rro":{"t":3.0},"Pon":{"d":3.0},"as ":{"B":1.0,"L":1.0},"eye":{"r":1.0}," Pa":{"s":2.0,"t":1.0}," Pl":{"a":1.0},"eys":{"\n":1.0}," Po":{"n":2.0},"aqu":{"i":1.0},"Aru":{"n":1.0},"Yar":{"d":1.0},"at ":{"C":1.0,"H":1.0,"M":1.0},"rso":{"n":1.0},"arb":{"o":1.0},"poo":{"l":1.0,"n":2.0},"ara":{"q":1.0,"\n":1.0},"ard":{"s":1.0,"e":2.0,"\n":1.0},"arh":{"a":1.0},"arr":{"i":2.0,"o":3.0},"y H":{"i":1.0},"art":{" ":1.0,"e":2.0,"i":3.0},"rte":{"r":2.0},"nla":{"n":1.0},"y L":{"a":2.0},"ppe":{"r":2.0}," Qu":{"a":1.0},"nle":{"y":1.0},"rti":{"n":3.0},"rth":{" ":2.0},"y M":{"a":1.0},"y O":{"n":1.0},"y T":{"w":1.0},"ppl":{"e":2.0},"ppo":{"o":1.0},"asa":{"n":1.0},"y W":{"i":1.0},"Rus":{"s":1.0},"ase":{"a":1.0,"y":1.0}," Re":{"e":1.0},"Han":{"d":1.0,"n":1.0},"Lit":{"t":4.0},"Har":{"b":1.0,"r":1.0},"Hav":{"e":1.0},"Haw":{"k":1.0},"ast":{" ":2.0,"u":2.0},"Pri":{"m":1.0,"n":1.0},"run":{"d":1.0,"k":2.0},"h B":{"a":1.0},"h H":{"i":1.0},"hal":{"w":1.0}," Se":{"t":3.0},"ate":{"r":1.0,"\n":6.0},"ath":{"\n":1.0},"han":{"n":1.0},"ham":{" ":2.0,"s":2.0}," Si":{"d":1.0},"ati":{"o":1.0},"h S":{"i":1.0,"o":3.0}," So":{"u":3.0},"h T":{"o":1.0}," Sp":{"r":2.0},"nna":{"h":1.0},"ll ":{"H":2.0}," Sw":{"a":1.0},"pri":{"n":3.0}," Ta":{"r":1.0},"nno":{"n":1.0},"Nor":{"t":2.0},"Not":{"t":1.0},"aug":{"h":1.0},"nny":{" ":1.0},"yde":{"n":2.0}," To":{"w":3.0}," Tr":{"e":1.0},"he ":{"B":2.0,"C":1.0,"S":1.0,"M":1.0}," Tw":{"o":1.0},"yds":{"\n":1.0},"non":{"\n":1.0},"Llo":{"y":1.0},"ave":{"r":1.0},"w B":{"u":1.0},"lla":{"s":1.0,"g":1.0,"\n":1.0},"wam":{"p":1.0},"lle":{" ":1.0,"y":1.0},"Hea":{"d":1.0,"l":1.0},"Hed":{"r":1.0},"yer":{"s":1.0},"llf":{"a":1.0},"ay ":{"T":1.0,"L":2.0,"O":1.0},"wat":{"e":1.0}," Va":{"l":1.0},"Fah":{"i":1.0},"Pur":{"c":1.0},"way":{"\n":1.0},"llo":{"w":1.0},"Hen":{"l":1.0},"Fan":{"n":1.0}," Vi":{"l":1.0},"awk":{"s":1.0},"Fat":{" ":1.0},"ns ":{"P":1.0,"B":1.0,"J":1.0},"aws":{"o":1.0}," Vu":{"e":1.0},"lmo":{"n":1.0},"fal":{"l":1.0}," Wi":{"l":1.0},"her":{" ":1.0,"s":1.0},"nt ":{"V":1.0,"H":1.0},"aya":{" ":1.0},"Lon":{"g":4.0},"Loo":{"k":1.0},"Low":{"e":2.0},"ayl":{"o":1.0},"f t":{"h":1.0},"Wes":{"t":1.0,"l":1.0}," Ya":{"r":1.0},"nso":{"n":1.0},"lor":{"s":1.0},"low":{"\n":1.0}," Yo":{"u":1.0},"loy":{"d":1.0},"nta":{"t":1.0,"i":1.0},"nte":{"r":1.0},"wel":{"l":1.0},"wer":{" ":2.0},"uar":{"t":1.0},"nto":{"s":1.0},"Hil":{"l":11.0},"ntr":{"y":1.0},"ntu":{"m":1.0},"Das":{"e":1.0},"Daw":{"s":1.0},"hie":{" ":1.0},"d B":{"a":2.0},"d P":{"l":1.0,"o":1.0},"d S":{"e":1.0},"d R":{"e":1.0},"d T":{"o":1.0},"Joe":{"s":1.0},"Joh":{"n":3.0},"Jos":{"i":1.0},"Wic":{"k":2.0},"ffs":{" ":1.0},"d o":{"f":1.0},"ny ":{"M":1.0},"Wil":{"l":1.0},"ylo":{"r":1.0},"Win":{"d":1.0},"lso":{"m":1.0},"jor":{" ":1.0},"yme":{"r":1.0},"s B":{"a":7.0,"o":1.0},"s C":{"a":2.0,"r":1.0},"s E":{"s":1.0},"s H":{"i":2.0,"o":2.0},"hn ":{"T":1.0},"s G":{"h":1.0},"s J":{"o":1.0},"win":{"e":1.0},"s L":{"a":1.0},"s N":{"e":1.0},"hn\u0027":{"s":1.0},"lth":{"y":1.0},"san":{"t":1.0},"ues":{" ":1.0},"s P":{"a":1.0},"s Q":{"u":1.0},"Bal":{"s":1.0,"l":1.0},"Bak":{"e":1.0},"s Y":{"o":1.0},"Ban":{"k":1.0},"Fis":{"h":2.0},"uff":{"s":1.0},"Bau":{"g":1.0},"Bay":{" ":2.0,"\n":28.0},"You":{"n":1.0},"lum":{" ":1.0},"del":{"l":2.0},"b H":{"i":1.0},"den":{" ":2.0,"\n":2.0},"se ":{"G":1.0},"der":{"s":1.0},"ugh":{"e":1.0},"Hod":{"g":3.0},"wks":{" ":1.0},"Hog":{"s":1.0},"Hol":{"e":1.0,"l":1.0},"Hop":{"e":2.0},"wn ":{"B":1.0},"hns":{"o":1.0},"bbs":{"\n":1.0},"lwe":{"l":1.0},"dge":{" ":1.0,"\u0027":1.0,"\n":1.0},"Set":{"t":3.0},"hom":{"a":1.0},"sea":{" ":1.0},"sel":{"l":1.0},"Dia":{"m":1.0},"uit":{"a":1.0},"sey":{"s":1.0},"Bel":{"l":1.0,"m":1.0},"sh ":{"B":1.0,"T":1.0},"Dix":{" ":1.0},"lyd":{"e":2.0},"um ":{"T":1.0},"Sha":{"n":1.0},"ber":{"t":1.0},"woo":{"d":1.0},"hre":{"l":1.0},"For":{"t":1.0},"Sid":{"e":1.0},"she":{"r":1.0},"ull":{" ":1.0},"shw":{"a":1.0},"sia":{"s":1.0},"oad":{" ":2.0},"ums":{" ":1.0},"Hun":{"t":1.0},"cIn":{"t":1.0},"und":{" ":1.0,"e":1.0,"\n":3.0},"od ":{"P":1.0},"Ske":{"l":1.0},"ung":{"\n":1.0},"fs ":{"B":1.0},"unk":{" ":2.0},"Fre":{"s":1.0,"e":1.0},"unt":{" ":1.0,"a":1.0,"r":1.0,"u":1.0},"hur":{"c":1.0},"hut":{"\n":5.0},"bio":{"n":1.0},"Sla":{"n":1.0},"ywi":{"n":1.0},"wso":{"n":1.0},"Upp":{"e":1.0},"ock":{"w":1.0},"oco":{"d":1.0},"dne":{"y":1.0},"Dot":{"y":1.0},"of ":{"t":1.0},"sle":{"y":1.0},"Mac":{" ":1.0},"ode":{"l":1.0},"hwa":{"t":1.0},"odg":{"e":3.0},"Maj":{"o":1.0},"Mar":{"t":3.0},"May":{"a":1.0},"Bly":{"d":2.0},"McI":{"n":1.0},"m E":{"s":1.0},"m G":{"h":1.0},"McN":{"a":1.0},"oes":{" ":1.0},"mas":{" ":1.0},"mar":{"a":1.0},"m T":{"r":1.0,"o":1.0},"urc":{"e":1.0,"h":1.0},"ure":{"\n":2.0},"urn":{"b":1.0},"mbe":{"r":1.0},"cNa":{"m":1.0},"Sou":{"t":2.0,"n":3.0},"hym":{"e":1.0},"Spa":{"n":1.0},"me ":{"B":1.0,"S":1.0},"ush":{"\n":2.0},"som":{" ":1.0,"e":2.0},"son":{" ":1.0,"\n":2.0},"Spo":{"o":1.0},"Spr":{"i":3.0},"uss":{"e":1.0},"dri":{"n":1.0},"ogs":{" ":1.0},"ogu":{"e":1.0},"Bon":{"d":1.0},"Bot":{"t":2.0},"uth":{" ":2.0},"Bow":{"a":1.0},"ohn":{" ":1.0,"s":1.0,"\u0027":1.0},"Mey":{"e":1.0},"dso":{"m":1.0},"ss ":{"Q":1.0},"bou":{"r":1.0},"k B":{"a":2.0},"Duf":{"f":1.0},"\nAl":{"b":1.0},"men":{"t":3.0},"\nAn":{"d":1.0},"\nAp":{"p":1.0},"mes":{" ":1.0},"\nAr":{"u":1.0},"mer":{"s":1.0},"st ":{"B":1.0,"E":2.0},"k V":{"i":1.0},"\nBa":{"u":1.0,"k":1.0,"l":2.0},"\nBe":{"l":2.0},"Bra":{"n":1.0},"\nBl":{"y":2.0},"\nBo":{"w":1.0}," of":{" ":1.0},"\nBr":{"a":1.0},"om ":{"G":1.0},"sse":{"l":1.0},"Ste":{"e":1.0,"v":1.0},"Old":{" ":1.0},"\nCa":{"p":1.0,"r":2.0,"n":1.0},"\nCh":{"a":1.0,"u":1.0},"\nCo":{"p":1.0,"c":1.0,"t":1.0,"o":1.0},"\nCr":{"a":1.0,"e":1.0},"on ":{"S":1.0,"G":2.0,"L":1.0},"sta":{"t":6.0},"\nDa":{"s":1.0,"w":1.0},"ole":{"\n":1.0},"dy ":{"H":1.0},"oll":{"o":1.0},"\nDi":{"a":1.0},"sto":{"w":1.0},"Mil":{"l":1.0},"Min":{"e":1.0},"\nDo":{"t":1.0},"stu":{"r":2.0},"\nDu":{"f":1.0},"oma":{"s":1.0},"\nEa":{"s":1.0},"ome":{" ":2.0},"One":{"\n":1.0},"\nEd":{"n":1.0},"kel":{"e":1.0},"iam":{"o":1.0},"ker":{"s":1.0,"i":1.0},"ias":{" ":1.0},"Swa":{"m":1.0},"Bus":{"h":2.0},"ona":{"r":1.0},"ond":{" ":1.0,"\n":4.0},"\nFa":{"t":1.0,"h":1.0,"n":1.0},"one":{"r":1.0},"ibb":{"s":1.0},"ong":{" ":4.0},"\nFi":{"s":2.0},"\nFo":{"r":1.0},"ont":{"\n":1.0},"ons":{" ":1.0},"\nFr":{"e":2.0},"bul":{"l":1.0},"dyw":{"i":1.0},"ie ":{"H":1.0},"ood":{" ":1.0},"\nGe":{"o":1.0},"ook":{"\n":1.0},"ool":{"\n":1.0},"oon":{"s":1.0,"e":1.0},"ick":{"e":1.0,"h":2.0}," th":{"e":1.0},"oot":{"e":1.0},"\nGr":{"e":4.0},"x B":{"a":1.0},"or ":{"B":1.0},"Qua":{"r":1.0},"\nHa":{"r":1.0,"v":1.0,"w":1.0,"n":2.0},"ope":{"\n":2.0},"kha":{"m":2.0},"\nHe":{"a":1.0,"d":1.0,"n":1.0},"ide":{"\n":1.0},"opp":{"e":1.0},"\nHo":{"d":3.0},"Kin":{"g":1.0},"\nHu":{"n":1.0},"Gar":{"d":2.0},"qui":{"t":1.0},"g B":{"a":2.0,"u":1.0},"\n\n\n":{"A":4.0,"B":10.0,"C":12.0,"D":5.0,"E":2.0,"F":8.0,"G":5.0,"H":12.0,"J":5.0,"K":1.0,"L":14.0,"M":9.0,"N":5.0,"O":1.0,"P":11.0,"R":8.0,"S":10.0,"T":12.0,"U":1.0,"V":1.0,"W":5.0},"g G":{"h":2.0},"g L":{"o":1.0},"gan":{" ":1.0},"ot ":{"B":3.0},"g S":{"w":1.0},"\nJa":{"m":1.0},"org":{"e":1.0},"\nJo":{"s":1.0,"h":3.0},"ort":{" ":1.0,"h":2.0},"ors":{" ":1.0},"Mou":{"n":2.0},"Val":{"l":1.0},"ose":{" ":1.0},"\n\nA":{"p":1.0,"r":1.0,"l":1.0,"n":1.0},"\n\nB":{"a":4.0,"r":1.0,"e":2.0,"l":2.0,"o":1.0},"iga":{"n":1.0},"Van":{"t":1.0},"\n\nC":{"a":4.0,"r":2.0,"h":2.0,"o":4.0},"ge ":{"E":1.0},"\n\nD":{"a":2.0,"u":1.0,"i":1.0,"o":1.0},"osi":{"a":1.0},"\n\nE":{"a":1.0,"d":1.0},"osh":{"\n":1.0},"ea ":{"E":1.0},"\n\nF":{"a":3.0,"r":2.0,"i":2.0,"o":1.0},"\n\nG":{"r":4.0,"e":1.0},"\n\nH":{"a":5.0,"e":3.0,"u":1.0,"o":3.0},"ge\u0027":{"s":1.0},"\nKi":{"n":1.0},"\n\nJ":{"a":1.0,"o":4.0},"\n\nK":{"i":1.0},"\n\nL":{"a":1.0,"e":2.0,"i":4.0,"l":1.0,"o":6.0},"mon":{"t":1.0,"d":1.0},"\n\nM":{"a":5.0,"c":2.0,"e":1.0,"o":1.0},"\n\nN":{"e":1.0,"i":1.0,"o":3.0},"oss":{"\n":1.0},"\n\nO":{"l":1.0},"\n\nP":{"a":3.0,"r":2.0,"u":1.0,"i":1.0,"l":2.0,"o":2.0},"\n\nR":{"e":2.0,"u":1.0,"h":1.0,"o":4.0},"\n\nS":{"p":3.0,"t":2.0,"h":1.0,"k":1.0,"l":1.0,"o":2.0},"\n\nT":{"a":2.0,"r":2.0,"u":1.0,"h":6.0,"o":1.0},"\n\nU":{"p":1.0},"\n\nV":{"a":1.0},"\n\nW":{"e":2.0,"i":3.0},"\nLa":{"m":1.0},"ote":{"n":1.0},"\nLe":{"t":1.0,"o":1.0},"\nLi":{"t":4.0},"\nLl":{"o":1.0},"\nLo":{"w":2.0,"n":4.0},"ott":{"i":1.0,"o":3.0},"Geo":{"r":1.0},"oty":{"\n":1.0},"Eas":{"t":1.0},"ms ":{"C":2.0,"G":1.0},"\nMa":{"r":3.0,"y":1.0,"j":1.0},"\nMc":{"I":1.0,"N":1.0},"\nMe":{"y":1.0},"e B":{"a":6.0,"o":2.0},"e A":{"p":1.0},"e D":{"i":1.0},"oun":{"d":4.0,"t":3.0,"g":1.0},"e C":{"a":1.0,"o":1.0},"ead":{" ":1.0},"e E":{"s":1.0},"e H":{"a":1.0,"i":1.0},"\nMo":{"u":1.0},"e G":{"a":2.0},"our":{"\n":1.0},"out":{"h":2.0},"eal":{"t":1.0},"ta ":{"B":1.0},"e M":{"i":1.0},"ges":{" ":1.0},"eas":{"a":1.0},"e S":{"e":2.0},"eat":{" ":2.0},"e V":{"u":1.0},"ove":{"r":1.0,"\n":1.0},"ed ":{"B":1.0},"\nNe":{"w":1.0},"\nNi":{"b":1.0},"\nNo":{"r":2.0,"t":1.0},"mro":{"s":1.0},"owa":{"y":1.0},"owe":{"r":2.0},"ee ":{"B":2.0},"Tar":{"r":1.0,"t":1.0},"own":{" ":1.0,"\n":4.0},"\nOl":{"d":1.0},"Tay":{"l":1.0},"Edn":{"e":1.0},"eco":{"v":1.0},"Ghu":{"t":5.0},"t C":{"a":1.0},"t B":{"a":4.0},"t E":{"n":2.0},"in ":{"S":1.0},"\nPa":{"r":2.0,"s":1.0},"t H":{"e":1.0,"i":1.0,"o":1.0},"tai":{"n":1.0},"ven":{"s":1.0},"t M":{"o":1.0},"gha":{"m":1.0},"ver":{"s":1.0,"y":1.0},"\nPi":{"c":1.0},"t P":{"a":1.0},"ghe":{"r":1.0},"tat":{"e":6.0,"i":1.0},"\nPl":{"e":1.0,"u":1.0},"ill":{"a":1.0,"\n":13.0},"\nPo":{"c":1.0,"n":1.0},"t V":{"a":1.0},"\nPr":{"i":2.0},"\nPu":{"r":1.0},"Can":{"e":1.0},"edr":{"i":1.0},"Cap":{"p":1.0},"Car":{"r":3.0,"t":1.0},"ks ":{"N":1.0},"Cay":{" ":2.0},"oyd":{"s":1.0},"eef":{"\n":1.0},"eek":{" ":1.0,"\n":1.0},"c H":{"i":1.0},"Int":{"o":1.0},"een":{" ":1.0,"l":1.0},"imr":{"o":1.0},"eep":{" ":1.0},"\nRe":{"c":1.0,"d":1.0},"ind":{"y":1.0},"inc":{"e":1.0},"\nRh":{"y":1.0},"ine":{" ":1.0,"\n":1.0},"ing":{" ":3.0,"s":1.0,"t":1.0,"h":1.0,"\n":1.0},"\nRo":{"a":2.0,"s":1.0,"g":1.0},"\nRu":{"s":1.0},"ins":{" ":1.0},"Vil":{"l":1.0},"\nSh":{"a":1.0}},"chainLength":3}